arches_querysets/__init__.py
arches_querysets/apps.py
arches_querysets/arches_querysets_urls.py
arches_querysets/celery.py
arches_querysets/fields.py
arches_querysets/hosts.py
arches_querysets/lookups.py
arches_querysets/models.py
arches_querysets/querysets.py
arches_querysets/settings.py
arches_querysets/settings_local.py
arches_querysets/urls.py
arches_querysets/wsgi.py
arches_querysets/bulk_operations/__init__.py
arches_querysets/bulk_operations/tiles.py
arches_querysets/datatypes/__init__.py
arches_querysets/datatypes/concept_types.py
arches_querysets/datatypes/datatypes.py
arches_querysets/datatypes/file.py
arches_querysets/datatypes/node_value.py
arches_querysets/datatypes/resource_types.py
arches_querysets/datatypes/string.py
arches_querysets/datatypes/url.py
arches_querysets/functions/__init__.py
arches_querysets/locale/.gitkeep
arches_querysets/management/__init__.py
arches_querysets/management/commands/__init__.py
arches_querysets/management/commands/add_test_data.py
arches_querysets/management/commands/delete_test_data.py
arches_querysets/media/css/themes/_project.scss
arches_querysets/media/img/favicon.png
arches_querysets/media/js/.gitkeep
arches_querysets/migrations/0001_initial.py
arches_querysets/migrations/__init__.py
arches_querysets/rest_framework/__init__.py
arches_querysets/rest_framework/field_mixins.py
arches_querysets/rest_framework/generic_views.py
arches_querysets/rest_framework/multipart_json_parser.py
arches_querysets/rest_framework/pagination.py
arches_querysets/rest_framework/permissions.py
arches_querysets/rest_framework/serializers.py
arches_querysets/rest_framework/utils.py
arches_querysets/rest_framework/view_mixins.py
arches_querysets/search_components/__init__.py
arches_querysets/search_indexes/__init__.py
arches_querysets/src/arches_querysets/declarations.d.ts
arches_querysets/system_settings/readme.txt
arches_querysets/utils/__init__.py
arches_querysets/utils/models.py
arches_querysets/utils/tests.py
arches_querysets-1.0.0.dist-info/licenses/LICENSE
arches_querysets-1.0.0.dist-info/METADATA
arches_querysets-1.0.0.dist-info/WHEEL
arches_querysets-1.0.0.dist-info/top_level.txt
arches_querysets-1.0.0.dist-info/RECORD
