Metadata-Version: 2.4
Name: arches-querysets
Version: 1.0.0
Summary: A Django-native interface for Arches implementers to express application logic, query business data, and build APIs.
Author: Arches Project
License-Expression: AGPL-3.0-or-later
Project-URL: Homepage, https://archesproject.org/
Project-URL: Documentation, https://arches.readthedocs.io
Project-URL: Repository, https://github.com/archesproject/arches-querysets.git
Project-URL: Issues, https://github.com/archesproject/arches-querysets/issues
Classifier: Development Status :: 4 - Beta
Classifier: Programming Language :: Python
Classifier: Programming Language :: Python :: 3
Classifier: Programming Language :: Python :: 3 :: Only
Classifier: Programming Language :: Python :: 3.10
Classifier: Programming Language :: Python :: 3.11
Classifier: Programming Language :: Python :: 3.12
Classifier: Programming Language :: Python :: 3.13
Classifier: Framework :: Django
Classifier: Framework :: Django :: 4.2
Classifier: Framework :: Django :: 5.2
Classifier: Intended Audience :: Developers
Requires-Python: >=3.10
License-File: LICENSE
Requires-Dist: arches!=8.0.0,<8.2.0,>=7.6.12
Provides-Extra: drf
Requires-Dist: djangorestframework~=3.16; extra == "drf"
Dynamic: license-file
